pkgsettings/__init__.py
pkgsettings/pkgsettings.py
pkgsettings/py.typed
pkgsettings-1.1.1.dist-info/LICENSE
pkgsettings-1.1.1.dist-info/METADATA
pkgsettings-1.1.1.dist-info/WHEEL
pkgsettings-1.1.1.dist-info/top_level.txt
pkgsettings-1.1.1.dist-info/RECORD
