Metadata-Version: 2.1
Name: pkgsettings
Version: 1.1.1
Summary: Python package to ease the configuration of packages
Home-page: https://github.com/kpn/py-pkgsettings
Author: KPN DE Platform
Author-email: de-platform@kpn.com
Classifier: Development Status :: 5 - Production/Stable
Classifier: Environment :: Web Environment
Classifier: Intended Audience :: Developers
Classifier: Operating System :: OS Independent
Classifier: License :: OSI Approved :: Apache Software License
Classifier: Programming Language :: Python
Classifier: Programming Language :: Python :: 3
Classifier: Programming Language :: Python :: 3.7
Classifier: Programming Language :: Python :: 3.8
Classifier: Programming Language :: Python :: 3.9
Classifier: Programming Language :: Python :: 3.10
Classifier: Topic :: Internet :: WWW/HTTP
Classifier: Topic :: Software Development :: Libraries :: Python Modules
License-File: LICENSE
Requires-Dist: typing-extensions (<5.0.0,>=4.5.0)
